halomod/__init__.py
halomod/_cli.py
halomod/bias.py
halomod/concentration.py
halomod/cross_correlations.py
halomod/functional.py
halomod/halo_exclusion.py
halomod/halo_model.py
halomod/hod.py
halomod/integrate_corr.py
halomod/profiles.py
halomod/tools.py
halomod/wdm.py
halomod/data/uKc_einasto.npz
halomod-2.2.2.dist-info/LICENSE.rst
halomod-2.2.2.dist-info/METADATA
halomod-2.2.2.dist-info/WHEEL
halomod-2.2.2.dist-info/top_level.txt
halomod-2.2.2.dist-info/RECORD
