Metadata-Version: 2.1
Name: halomod
Version: 2.2.2
Summary: A Halo Model calculator built on hmf
Author-email: Steven Murray <murray.steveng@gmail.com>
License: MIT
Classifier: Development Status :: 4 - Beta
Classifier: Intended Audience :: Science/Research
Classifier: License :: OSI Approved :: MIT License
Classifier: Operating System :: POSIX
Classifier: Operating System :: Unix
Classifier: Programming Language :: Python
Classifier: Programming Language :: Python :: 3
Classifier: Programming Language :: Python :: 3 :: Only
Classifier: Programming Language :: Python :: Implementation :: CPython
Classifier: Natural Language :: English
Classifier: Topic :: Scientific/Engineering :: Physics
Classifier: Topic :: Scientific/Engineering :: Astronomy
Requires-Python: >=3.8
License-File: LICENSE.rst
Requires-Dist: hmf
Requires-Dist: mpmath
Requires-Dist: numpy
Requires-Dist: scipy>=1.12
Requires-Dist: colossus
Requires-Dist: hankel
Provides-Extra: docs
Requires-Dist: Sphinx>=1.7.5; extra == "docs"
Requires-Dist: numpydoc>=0.8.0; extra == "docs"
Requires-Dist: nbsphinx; extra == "docs"
Requires-Dist: ipython; extra == "docs"
Requires-Dist: furo; extra == "docs"
Provides-Extra: tests
Requires-Dist: coverage>=4.5.1; extra == "tests"
Requires-Dist: pytest>=3.5.1; extra == "tests"
Requires-Dist: pytest-cov>=2.5.1; extra == "tests"
Requires-Dist: pytest-plt; extra == "tests"
Requires-Dist: pre-commit; extra == "tests"
Requires-Dist: mpmath>=1.0.0; extra == "tests"
Requires-Dist: numba; extra == "tests"
Provides-Extra: dev
Requires-Dist: halomod[docs,tests]; extra == "dev"
Provides-Extra: all
Requires-Dist: halomod[dev]; extra == "all"
Requires-Dist: camb<2.0,>1.0.0; extra == "all"
